mlx/__main__.py
mlx/_reprlib_fix.py
mlx/extension.py
mlx/py.typed
mlx/utils.py
mlx/include/cccl/cuda/__cccl_config
mlx/include/cccl/cuda/annotated_ptr
mlx/include/cccl/cuda/atomic
mlx/include/cccl/cuda/barrier
mlx/include/cccl/cuda/cmath
mlx/include/cccl/cuda/discard_memory
mlx/include/cccl/cuda/functional
mlx/include/cccl/cuda/latch
mlx/include/cccl/cuda/memory_resource
mlx/include/cccl/cuda/pipeline
mlx/include/cccl/cuda/ptx
mlx/include/cccl/cuda/semaphore
mlx/include/cccl/cuda/stream_ref
mlx/include/cccl/cuda/type_traits
mlx/include/cccl/cuda/version
mlx/include/cccl/cuda/__atomic/atomic.h
mlx/include/cccl/cuda/__barrier/aligned_size.h
mlx/include/cccl/cuda/__barrier/async_contract_fulfillment.h
mlx/include/cccl/cuda/__barrier/barrier.h
mlx/include/cccl/cuda/__barrier/barrier_arrive_tx.h
mlx/include/cccl/cuda/__barrier/barrier_block_scope.h
mlx/include/cccl/cuda/__barrier/barrier_expect_tx.h
mlx/include/cccl/cuda/__barrier/barrier_native_handle.h
mlx/include/cccl/cuda/__barrier/barrier_thread_scope.h
mlx/include/cccl/cuda/__cmath/ceil_div.h
mlx/include/cccl/cuda/__functional/address_stability.h
mlx/include/cccl/cuda/__functional/get_device_address.h
mlx/include/cccl/cuda/__functional/maximum.h
mlx/include/cccl/cuda/__functional/minimum.h
mlx/include/cccl/cuda/__functional/proclaim_return_type.h
mlx/include/cccl/cuda/__fwd/barrier.h
mlx/include/cccl/cuda/__fwd/barrier_native_handle.h
mlx/include/cccl/cuda/__fwd/pipeline.h
mlx/include/cccl/cuda/__latch/latch.h
mlx/include/cccl/cuda/__memcpy_async/completion_mechanism.h
mlx/include/cccl/cuda/__memcpy_async/cp_async_bulk_shared_global.h
mlx/include/cccl/cuda/__memcpy_async/cp_async_fallback.h
mlx/include/cccl/cuda/__memcpy_async/cp_async_shared_global.h
mlx/include/cccl/cuda/__memcpy_async/dispatch_memcpy_async.h
mlx/include/cccl/cuda/__memcpy_async/is_local_smem_barrier.h
mlx/include/cccl/cuda/__memcpy_async/memcpy_async.h
mlx/include/cccl/cuda/__memcpy_async/memcpy_async_barrier.h
mlx_cuda_12-0.30.1.dist-info/METADATA
mlx_cuda_12-0.30.1.dist-info/WHEEL
mlx_cuda_12-0.30.1.dist-info/top_level.txt
mlx_cuda_12-0.30.1.dist-info/RECORD
mlx_cuda_12-0.30.1.dist-info/licenses/LICENSE
mlx_cuda_12-0.30.1.dist-info/sboms/auditwheel.cdx.json
