Metadata-Version: 2.4
Name: mlx-cuda-12
Version: 0.30.1
Summary: A framework for machine learning on Apple silicon.
Home-page: https://github.com/ml-explore/mlx
Author: MLX Contributors
Author-email: mlx@group.apple.com
License: MIT
Requires-Python: >=3.10
License-File: LICENSE
Requires-Dist: nvidia-cublas-cu12==12.9.*
Requires-Dist: nvidia-cuda-nvrtc-cu12==12.9.*
Requires-Dist: nvidia-cudnn-cu12==9.*
Requires-Dist: nvidia-nccl-cu12
Dynamic: author
Dynamic: author-email
Dynamic: description
Dynamic: description-content-type
Dynamic: home-page
Dynamic: license
Dynamic: license-file
Dynamic: requires-dist
Dynamic: requires-python
Dynamic: summary
